jonf.py
jonf-0.0.7.dist-info/LICENSE
jonf-0.0.7.dist-info/WHEEL
jonf-0.0.7.dist-info/METADATA
jonf-0.0.7.dist-info/RECORD
