Metadata-Version: 2.1
Name: jonf
Version: 0.0.7
Summary: JONF parser/formatter in Python
Home-page: https://github.com/whyolet/jonf-py
License: MIT
Keywords: jonf,json,configuration,dsl,parser
Author: Denis Ryzhkov
Author-email: denisr@denisr.com
Requires-Python: >=3.8,<4.0
Classifier: License :: OSI Approved :: MIT License
Classifier: Programming Language :: Python :: 3
Classifier: Programming Language :: Python :: 3.10
Classifier: Programming Language :: Python :: 3.8
Classifier: Programming Language :: Python :: 3.9
Project-URL: Documentation, https://github.com/whyolet/jonf
Project-URL: Repository, https://github.com/whyolet/jonf-py
